ndfetcher/__init__.py
ndfetcher/data.py
ndfetcher/download.py
ndfetcher/find.py
ndfetcher-0.1.1.dist-info/LICENSE
ndfetcher-0.1.1.dist-info/METADATA
ndfetcher-0.1.1.dist-info/WHEEL
ndfetcher-0.1.1.dist-info/entry_points.txt
ndfetcher-0.1.1.dist-info/top_level.txt
ndfetcher-0.1.1.dist-info/RECORD
