Metadata-Version: 2.1
Name: ndfetcher
Version: 0.1.1
Summary: Fetching nuclear data
Author-email: Nicolas Linden <linden.nicolas@orange.fr>
Project-URL: Homepage, https://github.com/nplinden/ndfetcher
Classifier: Programming Language :: Python :: 3.7
Requires-Python: >=3.7
License-File: LICENSE
